{
  "name": {
    "precision": 1.0,
    "recall": 1.0,
    "f1-score": 1.0,
    "support": 4
  },
  "act": {
    "precision": 1.0,
    "recall": 1.0,
    "f1-score": 1.0,
    "support": 6
  },
  "problem": {
    "precision": 1.0,
    "recall": 1.0,
    "f1-score": 1.0,
    "support": 4
  },
  "micro avg": {
    "precision": 1.0,
    "recall": 1.0,
    "f1-score": 1.0,
    "support": 14
  },
  "macro avg": {
    "precision": 1.0,
    "recall": 1.0,
    "f1-score": 1.0,
    "support": 14
  },
  "weighted avg": {
    "precision": 1.0,
    "recall": 1.0,
    "f1-score": 1.0,
    "support": 14
  }
}